{
    "id": 191,
    "name": "luoyin",
    "form": "default",
    "main_type": {
        "id": 6,
        "name": "Ground",
        "localized": {
            "zh": "地"
        }
    },
    "sub_type": {
        "id": 16,
        "name": "Dark",
        "localized": {
            "zh": "恶"
        }
    },
    "default_legacy_type": {
        "id": 6,
        "name": "Ground",
        "localized": {
            "zh": "地"
        }
    },
    "leader_potential": false,
    "is_leader_form": false,
    "preferred_attack_style": "Physical",
    "localized": {
        "zh": {
            "name": "罗隐"
        }
    },
    "base_hp": 107,
    "base_phy_atk": 159,
    "base_mag_atk": 78,
    "base_phy_def": 112,
    "base_mag_def": 70,
    "base_spd": 75,
    "evolves_from_id": 190,
    "species": {
        "id": 47,
        "name": "Amiyat",
        "localized": {
            "zh": "阿米亚特"
        }
    },
    "trait": {
        "id": 63,
        "name": "Stone Feast",
        "description": "When energy is insufficient, consumes 5% of HP to replace 1 energy.",
        "localized": {
            "zh": {
                "name": "石头大餐",
                "description": "能量不足时，消耗5%生命，代替1能量。"
            }
        }
    },
    "move_pool": [
        {
            "id": 419,
            "name": "Demon Claw",
            "move_type": {
                "id": 16,
                "name": "Dark",
                "localized": {
                    "zh": "恶"
                }
            },
            "localized": {
                "zh": {
                    "name": "魔爪",
                    "description": "造成物伤，自己回复1能量。"
                }
            },
            "move_category": "Physical Attack",
            "energy_cost": 0,
            "power": 30,
            "description": "Deals physical damage. User restores 1 energy."
        },
        {
            "id": 408,
            "name": "Bat",
            "move_type": {
                "id": 16,
                "name": "Dark",
                "localized": {
                    "zh": "恶"
                }
            },
            "localized": {
                "zh": {
                    "name": "蝙蝠",
                    "description": "造成物伤，吸血100%。"
                }
            },
            "move_category": "Physical Attack",
            "energy_cost": 2,
            "power": 60,
            "description": "Deals physical damage with 100% Lifesteal."
        },
        {
            "id": 426,
            "name": "Greed",
            "move_type": {
                "id": 16,
                "name": "Dark",
                "localized": {
                    "zh": "恶"
                }
            },
            "localized": {
                "zh": {
                    "name": "贪婪",
                    "description": "获得100%吸血。"
                }
            },
            "move_category": "Status",
            "energy_cost": 2,
            "power": null,
            "description": "Gains Lifesteal +100%."
        },
        {
            "id": 30,
            "name": "Power Boost",
            "move_type": {
                "id": 1,
                "name": "Normal",
                "localized": {
                    "zh": "普通"
                }
            },
            "localized": {
                "zh": {
                    "name": "力量增效",
                    "description": "自己获得物攻+100%。"
                }
            },
            "move_category": "Status",
            "energy_cost": 1,
            "power": null,
            "description": "User's Physical Attack +100%."
        },
        {
            "id": 60,
            "name": "Preemptive Strike",
            "move_type": {
                "id": 1,
                "name": "Normal",
                "localized": {
                    "zh": "普通"
                }
            },
            "localized": {
                "zh": {
                    "name": "先发制人",
                    "description": "造成物理伤害，先手+1。"
                }
            },
            "move_category": "Physical Attack",
            "energy_cost": 2,
            "power": 55,
            "description": "Deals physical damage. Priority +1."
        },
        {
            "id": 215,
            "name": "Equilibrium",
            "move_type": {
                "id": 6,
                "name": "Ground",
                "localized": {
                    "zh": "地"
                }
            },
            "localized": {
                "zh": {
                    "name": "钧势",
                    "description": "自己获得物防+140%和速度-30。"
                }
            },
            "move_category": "Status",
            "energy_cost": 3,
            "power": null,
            "description": "User gains Physical Defense +140% and Speed -30."
        },
        {
            "id": 198,
            "name": "Sand Trap",
            "move_type": {
                "id": 6,
                "name": "Ground",
                "localized": {
                    "zh": "地"
                }
            },
            "localized": {
                "zh": {
                    "name": "鸣沙陷阱",
                    "description": "造成物伤，物防比敌方越高，本次技能威力越高。"
                }
            },
            "move_category": "Physical Attack",
            "energy_cost": 4,
            "power": 60,
            "description": "Deals physical damage. The higher user's Physical Defense than opponent's, the higher the power."
        },
        {
            "id": 417,
            "name": "Power Devour",
            "move_type": {
                "id": 16,
                "name": "Dark",
                "localized": {
                    "zh": "恶"
                }
            },
            "localized": {
                "zh": {
                    "name": "力量吞噬",
                    "description": "敌方获得技能威力-20，自己获得技能威力+20。"
                }
            },
            "move_category": "Status",
            "energy_cost": 4,
            "power": null,
            "description": "Opponent gains Move Power -20. User gains Move Power +20."
        },
        {
            "id": 209,
            "name": "Earthen Strike",
            "move_type": {
                "id": 6,
                "name": "Ground",
                "localized": {
                    "zh": "地"
                }
            },
            "localized": {
                "zh": {
                    "name": "岩土暴击",
                    "description": "造成物伤，每被攻击1次，本技能能耗永久-1。"
                }
            },
            "move_category": "Physical Attack",
            "energy_cost": 8,
            "power": 140,
            "description": "Deals physical damage. Each time the user is attacked, this move's energy cost -1 permanently."
        },
        {
            "id": 3506,
            "name": "Gravel Charge",
            "move_type": {
                "id": 6,
                "name": "Ground",
                "localized": {
                    "zh": "地"
                }
            },
            "localized": {
                "zh": {
                    "name": "砂石冲撞",
                    "description": "造成物伤，应对状态：敌方获得物防-80%。"
                }
            },
            "move_category": "Physical Attack",
            "energy_cost": 3,
            "power": 80,
            "description": "Deals physical damage. Counter Status: opponent gains Physical Defense -80%."
        },
        {
            "id": 201,
            "name": "Mud Armor",
            "move_type": {
                "id": 6,
                "name": "Ground",
                "localized": {
                    "zh": "地"
                }
            },
            "localized": {
                "zh": {
                    "name": "泥浆铠甲",
                    "description": "自己获得物攻和物防+40%，应对防御：额外使自己的增益翻倍。"
                }
            },
            "move_category": "Status",
            "energy_cost": 2,
            "power": null,
            "description": "User gains Physical Attack +50% and Physical Defense +50%. Counter Defense: user's Buffs are doubled."
        },
        {
            "id": 405,
            "name": "Dark Ambush",
            "move_type": {
                "id": 16,
                "name": "Dark",
                "localized": {
                    "zh": "恶"
                }
            },
            "localized": {
                "zh": {
                    "name": "暗突袭",
                    "description": "造成物伤，吸血50%，应对状态：本次技能威力翻倍。"
                }
            },
            "move_category": "Physical Attack",
            "energy_cost": 4,
            "power": 70,
            "description": "Deals physical damage with 50% Lifesteal. Counter Status: this move's power is doubled."
        },
        {
            "id": 190,
            "name": "Ground Spikes",
            "move_type": {
                "id": 6,
                "name": "Ground",
                "localized": {
                    "zh": "地"
                }
            },
            "localized": {
                "zh": {
                    "name": "地刺",
                    "description": "造成物伤，应对状态：额外打断被应对技能。"
                }
            },
            "move_category": "Physical Attack",
            "energy_cost": 3,
            "power": 95,
            "description": "Deals physical damage. Counter Status: additionally Interrupt the countered move."
        },
        {
            "id": 192,
            "name": "Earthquake",
            "move_type": {
                "id": 6,
                "name": "Ground",
                "localized": {
                    "zh": "地"
                }
            },
            "localized": {
                "zh": {
                    "name": "地震",
                    "description": "对敌方精灵造成物理伤害。"
                }
            },
            "move_category": "Physical Attack",
            "energy_cost": 10,
            "power": 190,
            "description": "Deals physical damage to the opponent."
        }
    ],
    "move_stones": [
        {
            "id": 48,
            "name": "Sharp Eyes",
            "move_type": {
                "id": 1,
                "name": "Normal",
                "localized": {
                    "zh": "普通"
                }
            },
            "localized": {
                "zh": {
                    "name": "锐利眼神",
                    "description": "敌方获得物防和魔防-120%。"
                }
            },
            "move_category": "Status",
            "energy_cost": 2,
            "power": null,
            "description": "Opponent gains Defense -120%."
        },
        {
            "id": 14,
            "name": "Defend",
            "move_type": {
                "id": 1,
                "name": "Normal",
                "localized": {
                    "zh": "普通"
                }
            },
            "localized": {
                "zh": {
                    "name": "防御",
                    "description": "减伤70%，应对攻击。"
                }
            },
            "move_category": "Defense",
            "energy_cost": 1,
            "power": null,
            "description": "Damage taken -70%. Counter Attack."
        },
        {
            "id": 27,
            "name": "Borrow",
            "move_type": {
                "id": 1,
                "name": "Normal",
                "localized": {
                    "zh": "普通"
                }
            },
            "localized": {
                "zh": {
                    "name": "借用",
                    "description": "每回合随机变成己方队伍中其他精灵的技能。"
                }
            },
            "move_category": "Status",
            "energy_cost": 0,
            "power": null,
            "description": "At the start of each turn, this move becomes a random move carried by a teammate."
        },
        {
            "id": 20,
            "name": "Reversal",
            "move_type": {
                "id": 1,
                "name": "Normal",
                "localized": {
                    "zh": "普通"
                }
            },
            "localized": {
                "zh": {
                    "name": "后发制人",
                    "description": "造成物理伤害，先手-1。"
                }
            },
            "move_category": "Physical Attack",
            "energy_cost": 3,
            "power": 140,
            "description": "Deals physical damage. Priority -1."
        },
        {
            "id": 24,
            "name": "Fortify",
            "move_type": {
                "id": 1,
                "name": "Normal",
                "localized": {
                    "zh": "普通"
                }
            },
            "localized": {
                "zh": {
                    "name": "加固",
                    "description": "自己获得物防+140%。"
                }
            },
            "move_category": "Status",
            "energy_cost": 2,
            "power": null,
            "description": "User's Physical Defense +140%."
        },
        {
            "id": 18,
            "name": "Encourage",
            "move_type": {
                "id": 1,
                "name": "Normal",
                "localized": {
                    "zh": "普通"
                }
            },
            "localized": {
                "zh": {
                    "name": "鼓劲",
                    "description": "自己获得魔防+150%。"
                }
            },
            "move_category": "Status",
            "energy_cost": 3,
            "power": null,
            "description": "User's Magic Defense +150%."
        },
        {
            "id": 76,
            "name": "Prevention Protocol",
            "move_type": {
                "id": 1,
                "name": "Normal",
                "localized": {
                    "zh": "普通"
                }
            },
            "localized": {
                "zh": {
                    "name": "有效预防",
                    "description": "减伤50%，应对攻击：下一次行动获得先手+1。"
                }
            },
            "move_category": "Defense",
            "energy_cost": 1,
            "power": null,
            "description": "Damage taken -50%. Counter Attack: next turn, user gains Priority +1."
        },
        {
            "id": 135,
            "name": "Flash Burn",
            "move_type": {
                "id": 3,
                "name": "Fire",
                "localized": {
                    "zh": "火"
                }
            },
            "localized": {
                "zh": {
                    "name": "闪燃",
                    "description": "造成物伤，应对状态：本次技能威力变为4倍。"
                }
            },
            "move_category": "Physical Attack",
            "energy_cost": 1,
            "power": 35,
            "description": "Deals physical damage. Counter Status: move power x4."
        },
        {
            "id": 124,
            "name": "Flame Cut",
            "move_type": {
                "id": 3,
                "name": "Fire",
                "localized": {
                    "zh": "火"
                }
            },
            "localized": {
                "zh": {
                    "name": "火焰切割",
                    "description": "对敌方精灵造成物理伤害。"
                }
            },
            "move_category": "Physical Attack",
            "energy_cost": 3,
            "power": 100,
            "description": "Deals physical damage to the opponent."
        },
        {
            "id": 130,
            "name": "Rage",
            "move_type": {
                "id": 3,
                "name": "Fire",
                "localized": {
                    "zh": "火"
                }
            },
            "localized": {
                "zh": {
                    "name": "怒火",
                    "description": "自己获得双攻+130%和双防-40%。"
                }
            },
            "move_category": "Status",
            "energy_cost": 1,
            "power": null,
            "description": "User gains Attack +130% and Defense -40%."
        },
        {
            "id": 191,
            "name": "Pitfall",
            "move_type": {
                "id": 6,
                "name": "Ground",
                "localized": {
                    "zh": "地"
                }
            },
            "localized": {
                "zh": {
                    "name": "地陷",
                    "description": "造成物伤，自己获得物防+60%，应对状态：本次技能威力翻倍，且物防额外+60%。"
                }
            },
            "move_category": "Physical Attack",
            "energy_cost": 5,
            "power": 70,
            "description": "Deals physical damage. Gains Physical Defense +60%. Counter Status: this move's power is doubled, and Physical Defense +60% additionally."
        },
        {
            "id": 206,
            "name": "Stone Skin",
            "move_type": {
                "id": 6,
                "name": "Ground",
                "localized": {
                    "zh": "地"
                }
            },
            "localized": {
                "zh": {
                    "name": "石肤术",
                    "description": "自己获得物防+160%和魔防-60%。"
                }
            },
            "move_category": "Status",
            "energy_cost": 3,
            "power": null,
            "description": "User gains Physical Defense +160% and Magic Defense -60%."
        },
        {
            "id": 331,
            "name": "Counter Punch",
            "move_type": {
                "id": 12,
                "name": "Fighting",
                "localized": {
                    "zh": "武"
                }
            },
            "localized": {
                "zh": {
                    "name": "反击拳",
                    "description": "造成物伤，2连击，若后手攻击，改为3连击。"
                }
            },
            "move_category": "Physical Attack",
            "energy_cost": 2,
            "power": 25,
            "description": "Deals physical damage, 2 Combo. If this move goes last, changes to 3 Combo."
        },
        {
            "id": 407,
            "name": "Otherworldly Hand",
            "move_type": {
                "id": 16,
                "name": "Dark",
                "localized": {
                    "zh": "恶"
                }
            },
            "localized": {
                "zh": {
                    "name": "彼岸之手",
                    "description": "造成物伤，自己每失去10%生命，本技能能耗-1。"
                }
            },
            "move_category": "Physical Attack",
            "energy_cost": 10,
            "power": 150,
            "description": "Deals physical damage. For every 10% HP lost by the user, this move's energy cost -1."
        }
    ],
    "legacy_moves": [
        {
            "monster_id": 191,
            "type_id": 2,
            "move_id": 93
        },
        {
            "monster_id": 191,
            "type_id": 1,
            "move_id": 62
        },
        {
            "monster_id": 191,
            "type_id": 3,
            "move_id": 123
        },
        {
            "monster_id": 191,
            "type_id": 4,
            "move_id": 150
        },
        {
            "monster_id": 191,
            "type_id": 5,
            "move_id": 184
        },
        {
            "monster_id": 191,
            "type_id": 6,
            "move_id": 194
        },
        {
            "monster_id": 191,
            "type_id": 7,
            "move_id": 224
        },
        {
            "monster_id": 191,
            "type_id": 8,
            "move_id": 257
        },
        {
            "monster_id": 191,
            "type_id": 9,
            "move_id": 279
        },
        {
            "monster_id": 191,
            "type_id": 10,
            "move_id": 291
        },
        {
            "monster_id": 191,
            "type_id": 11,
            "move_id": 320
        },
        {
            "monster_id": 191,
            "type_id": 12,
            "move_id": 328
        },
        {
            "monster_id": 191,
            "type_id": 13,
            "move_id": 354
        },
        {
            "monster_id": 191,
            "type_id": 14,
            "move_id": 378
        },
        {
            "monster_id": 191,
            "type_id": 15,
            "move_id": 400
        },
        {
            "monster_id": 191,
            "type_id": 16,
            "move_id": 410
        },
        {
            "monster_id": 191,
            "type_id": 17,
            "move_id": 446
        },
        {
            "monster_id": 191,
            "type_id": 18,
            "move_id": 467
        }
    ],
    "evolution_tree": {
        "stages": [
            {
                "depth": 0,
                "monsters": [
                    {
                        "id": 189,
                        "name": "amiyate",
                        "form": "default",
                        "localized": {
                            "zh": {
                                "name": "阿米亚特"
                            }
                        },
                        "is_leader_form": false,
                        "main_type": {
                            "id": 6,
                            "name": "Ground",
                            "localized": {
                                "zh": "地"
                            }
                        },
                        "sub_type": null
                    }
                ]
            },
            {
                "depth": 1,
                "monsters": [
                    {
                        "id": 190,
                        "name": "amiying",
                        "form": "default",
                        "localized": {
                            "zh": {
                                "name": "阿米樱"
                            }
                        },
                        "is_leader_form": false,
                        "main_type": {
                            "id": 6,
                            "name": "Ground",
                            "localized": {
                                "zh": "地"
                            }
                        },
                        "sub_type": null
                    }
                ]
            },
            {
                "depth": 2,
                "monsters": [
                    {
                        "id": 191,
                        "name": "luoyin",
                        "form": "default",
                        "localized": {
                            "zh": {
                                "name": "罗隐"
                            }
                        },
                        "is_leader_form": false,
                        "main_type": {
                            "id": 6,
                            "name": "Ground",
                            "localized": {
                                "zh": "地"
                            }
                        },
                        "sub_type": {
                            "id": 16,
                            "name": "Dark",
                            "localized": {
                                "zh": "恶"
                            }
                        }
                    }
                ]
            }
        ],
        "max_depth": 2,
        "total_unique_monsters": 3,
        "species_id": 47,
        "current_monster_id": 191
    },
    "world_profile": {
        "type_desc": "石头精灵",
        "description_habitat": "偶见于山地、雪山",
        "introduction": "身体中结晶脉络光滑透亮，十分坚硬，似乎是某种矿石。长着凶狠的样貌，揣着不知如何表达的善意，示好的时候会展示一下由石头构成的肌肉。",
        "refresh_locations": [
            "恶水沼泽",
            "风息山口",
            "晨曦山"
        ],
        "movement_type": "步行",
        "classis_id": 7,
        "classis_name": "岩石类精灵",
        "handbook_area_ids": [
            1,
            2
        ]
    },
    "breeding": null,
    "breeding_profile": {
        "pet_base_id": 3016,
        "egg_groups": [
            11,
            2
        ],
        "proportion_male": 8,
        "male_rate": 80,
        "female_rate": 20
    }
}
