{
    "id": 24,
    "name": "kakake_tuipi",
    "form": "Molting",
    "main_type": {
        "id": 4,
        "name": "Water",
        "localized": {
            "zh": "水"
        }
    },
    "sub_type": null,
    "default_legacy_type": {
        "id": 4,
        "name": "Water",
        "localized": {
            "zh": "水"
        }
    },
    "leader_potential": false,
    "is_leader_form": false,
    "preferred_attack_style": "Magic",
    "localized": {
        "zh": {
            "form": "蜕皮时的样子",
            "name": "咔咔壳"
        }
    },
    "base_hp": 90,
    "base_phy_atk": 37,
    "base_mag_atk": 96,
    "base_phy_def": 85,
    "base_mag_def": 107,
    "base_spd": 60,
    "evolves_from_id": 22,
    "species": {
        "id": 6,
        "name": "Plankshell",
        "localized": {
            "zh": "板板壳"
        }
    },
    "trait": {
        "id": 11,
        "name": "Shell Retraction",
        "description": "Move energy cost of carried Defense moves -2.",
        "localized": {
            "zh": {
                "name": "缩壳",
                "description": "携带的防御技能能耗-2。"
            }
        }
    },
    "move_pool": [
        {
            "id": 14,
            "name": "Defend",
            "move_type": {
                "id": 1,
                "name": "Normal",
                "localized": {
                    "zh": "普通"
                }
            },
            "localized": {
                "zh": {
                    "name": "防御",
                    "description": "减伤70%，应对攻击。"
                }
            },
            "move_category": "Defense",
            "energy_cost": 1,
            "power": null,
            "description": "Damage taken -70%. Counter Attack."
        },
        {
            "id": 148,
            "name": "Soap Bubble",
            "move_type": {
                "id": 4,
                "name": "Water",
                "localized": {
                    "zh": "水"
                }
            },
            "localized": {
                "zh": {
                    "name": "肥皂泡",
                    "description": "对敌方精灵造成魔法伤害。"
                }
            },
            "move_category": "Magic Attack",
            "energy_cost": 1,
            "power": 60,
            "description": "Deals magic damage to the opponent."
        },
        {
            "id": 36,
            "name": "Magic Boost",
            "move_type": {
                "id": 1,
                "name": "Normal",
                "localized": {
                    "zh": "普通"
                }
            },
            "localized": {
                "zh": {
                    "name": "魔法增效",
                    "description": "自己获得魔攻+70%。"
                }
            },
            "move_category": "Status",
            "energy_cost": 0,
            "power": null,
            "description": "User's Magic Attack +70%."
        },
        {
            "id": 152,
            "name": "Bubble",
            "move_type": {
                "id": 4,
                "name": "Water",
                "localized": {
                    "zh": "水"
                }
            },
            "localized": {
                "zh": {
                    "name": "气泡",
                    "description": "对敌方精灵造成魔法伤害。"
                }
            },
            "move_category": "Magic Attack",
            "energy_cost": 3,
            "power": 100,
            "description": "Deals magic damage to the opponent."
        },
        {
            "id": 168,
            "name": "Baptism",
            "move_type": {
                "id": 4,
                "name": "Water",
                "localized": {
                    "zh": "水"
                }
            },
            "localized": {
                "zh": {
                    "name": "洗礼",
                    "description": "驱散自己的减益，并获得全技能能耗-1。"
                }
            },
            "move_category": "Status",
            "energy_cost": 1,
            "power": null,
            "description": "Dispels all user's Debuffs. Gains Move Energy Cost -1."
        },
        {
            "id": 20,
            "name": "Reversal",
            "move_type": {
                "id": 1,
                "name": "Normal",
                "localized": {
                    "zh": "普通"
                }
            },
            "localized": {
                "zh": {
                    "name": "后发制人",
                    "description": "造成物理伤害，先手-1。"
                }
            },
            "move_category": "Physical Attack",
            "energy_cost": 3,
            "power": 140,
            "description": "Deals physical damage. Priority -1."
        },
        {
            "id": 164,
            "name": "Bubble Shield",
            "move_type": {
                "id": 4,
                "name": "Water",
                "localized": {
                    "zh": "水"
                }
            },
            "localized": {
                "zh": {
                    "name": "水泡盾",
                    "description": "减伤70%，应对攻击：自己获得魔攻+40%。"
                }
            },
            "move_category": "Defense",
            "energy_cost": 2,
            "power": null,
            "description": "Damage taken -70%. Counter Attack: user gains Magic Attack +40%."
        },
        {
            "id": 160,
            "name": "Aqua Flash",
            "move_type": {
                "id": 4,
                "name": "Water",
                "localized": {
                    "zh": "水"
                }
            },
            "localized": {
                "zh": {
                    "name": "水光冲击",
                    "description": "对敌方精灵造成魔法伤害。"
                }
            },
            "move_category": "Magic Attack",
            "energy_cost": 5,
            "power": 140,
            "description": "Deals magic damage to the opponent."
        },
        {
            "id": 153,
            "name": "Rain Dance",
            "move_type": {
                "id": 4,
                "name": "Water",
                "localized": {
                    "zh": "水"
                }
            },
            "localized": {
                "zh": {
                    "name": "落雨",
                    "description": "将天气改为雨天，持续8回合。"
                }
            },
            "move_category": "Status",
            "energy_cost": 5,
            "power": null,
            "description": "Changes weather to Rain for 8 turns."
        },
        {
            "id": 165,
            "name": "Hydro Cannon",
            "move_type": {
                "id": 4,
                "name": "Water",
                "localized": {
                    "zh": "水"
                }
            },
            "localized": {
                "zh": {
                    "name": "水炮",
                    "description": "造成魔伤，每次使用后，本技能能耗永久-1。"
                }
            },
            "move_category": "Magic Attack",
            "energy_cost": 5,
            "power": 110,
            "description": "Deals magic damage. After each use, this move's energy cost -1 permanently."
        },
        {
            "id": 151,
            "name": "Bubble Mirage",
            "move_type": {
                "id": 4,
                "name": "Water",
                "localized": {
                    "zh": "水"
                }
            },
            "localized": {
                "zh": {
                    "name": "泡沫幻影",
                    "description": "减伤70%，应对攻击：自己脱离。"
                }
            },
            "move_category": "Defense",
            "energy_cost": 2,
            "power": null,
            "description": "Damage taken -70%. Counter Attack: causes the user to Exit."
        },
        {
            "id": 167,
            "name": "Cataclysm",
            "move_type": {
                "id": 4,
                "name": "Water",
                "localized": {
                    "zh": "水"
                }
            },
            "localized": {
                "zh": {
                    "name": "天洪",
                    "description": "造成魔伤，应对状态：本技能能耗永久-6。"
                }
            },
            "move_category": "Magic Attack",
            "energy_cost": 7,
            "power": 140,
            "description": "Deals magic damage. Counter Status: this move's energy cost -6 permanently."
        },
        {
            "id": 162,
            "name": "Aqua Ring",
            "move_type": {
                "id": 4,
                "name": "Water",
                "localized": {
                    "zh": "水"
                }
            },
            "localized": {
                "zh": {
                    "name": "水环",
                    "description": "减伤70%，应对攻击：自己获得全技能能耗-2。"
                }
            },
            "move_category": "Defense",
            "energy_cost": 2,
            "power": null,
            "description": "Damage taken -70%. Counter Attack: user gains Move Energy Cost -2."
        }
    ],
    "move_stones": [
        {
            "id": 55,
            "name": "Assault",
            "move_type": {
                "id": 1,
                "name": "Normal",
                "localized": {
                    "zh": "普通"
                }
            },
            "localized": {
                "zh": {
                    "name": "突袭",
                    "description": "造成魔伤，应对状态：本次技能威力变为3倍。"
                }
            },
            "move_category": "Magic Attack",
            "energy_cost": 2,
            "power": 50,
            "description": "Deals magic damage. Counter Status: move power x3."
        },
        {
            "id": 37,
            "name": "Mana Burst",
            "move_type": {
                "id": 1,
                "name": "Normal",
                "localized": {
                    "zh": "普通"
                }
            },
            "localized": {
                "zh": {
                    "name": "魔能爆",
                    "description": "造成魔伤，释放时消耗所有能量，消耗越多，伤害越高。"
                }
            },
            "move_category": "Magic Attack",
            "energy_cost": 0,
            "power": 1,
            "description": "Deals magic damage. Consumes all energy when used. The more energy consumed, the higher the damage."
        },
        {
            "id": 13,
            "name": "Counter Guard",
            "move_type": {
                "id": 1,
                "name": "Normal",
                "localized": {
                    "zh": "普通"
                }
            },
            "localized": {
                "zh": {
                    "name": "防反",
                    "description": "减伤60%，应对攻击：自己获得物攻和魔攻+40%。"
                }
            },
            "move_category": "Defense",
            "energy_cost": 2,
            "power": null,
            "description": "Damage taken -60%. Counter Attack: gains Attack +60%."
        },
        {
            "id": 58,
            "name": "Fearless Heart",
            "move_type": {
                "id": 1,
                "name": "Normal",
                "localized": {
                    "zh": "普通"
                }
            },
            "localized": {
                "zh": {
                    "name": "无畏之心",
                    "description": "减伤100%，应对攻击：减免的伤害变为回复自己生命，且本技能能耗永久+2。"
                }
            },
            "move_category": "Defense",
            "energy_cost": 5,
            "power": null,
            "description": "Damage taken -100%. Counter Attack: the damage reduced is converted to HP recovery for the user, and this move's energy cost +2 permanently."
        },
        {
            "id": 16,
            "name": "Rewrite",
            "move_type": {
                "id": 1,
                "name": "Normal",
                "localized": {
                    "zh": "普通"
                }
            },
            "localized": {
                "zh": {
                    "name": "复写",
                    "description": "每回合随机变成自己未携带的技能，且该技能能耗-2。"
                }
            },
            "move_category": "Status",
            "energy_cost": 0,
            "power": null,
            "description": "Each turn, this move becomes a random uncarried move from this monster, and its energy cost -2."
        },
        {
            "id": 76,
            "name": "Prevention Protocol",
            "move_type": {
                "id": 1,
                "name": "Normal",
                "localized": {
                    "zh": "普通"
                }
            },
            "localized": {
                "zh": {
                    "name": "有效预防",
                    "description": "减伤50%，应对攻击：下一次行动获得先手+1。"
                }
            },
            "move_category": "Defense",
            "energy_cost": 1,
            "power": null,
            "description": "Damage taken -50%. Counter Attack: next turn, user gains Priority +1."
        },
        {
            "id": 100,
            "name": "Enzyme Control",
            "move_type": {
                "id": 2,
                "name": "Grass",
                "localized": {
                    "zh": "草"
                }
            },
            "localized": {
                "zh": {
                    "name": "酶浓度调整",
                    "description": "减伤70%，应对攻击：自己回复20%生命。"
                }
            },
            "move_category": "Defense",
            "energy_cost": 3,
            "power": null,
            "description": "Damage taken -70%. Counter Attack: restores 25% HP."
        },
        {
            "id": 95,
            "name": "Thorn Spike",
            "move_type": {
                "id": 2,
                "name": "Grass",
                "localized": {
                    "zh": "草"
                }
            },
            "localized": {
                "zh": {
                    "name": "棘突",
                    "description": "对敌方精灵造成魔法伤害。"
                }
            },
            "move_category": "Magic Attack",
            "energy_cost": 3,
            "power": 100,
            "description": "Deals magic damage to the opponent."
        },
        {
            "id": 334,
            "name": "Transform Power",
            "move_type": {
                "id": 12,
                "name": "Fighting",
                "localized": {
                    "zh": "武"
                }
            },
            "localized": {
                "zh": {
                    "name": "化劲",
                    "description": "获得全技能威力+40。"
                }
            },
            "move_category": "Status",
            "energy_cost": 2,
            "power": null,
            "description": "User gains Move Power +40."
        },
        {
            "id": 347,
            "name": "Iron Gate",
            "move_type": {
                "id": 12,
                "name": "Fighting",
                "localized": {
                    "zh": "武"
                }
            },
            "localized": {
                "zh": {
                    "name": "硬门",
                    "description": "应对攻击：打断被应对技能，并造成75威力物伤。"
                }
            },
            "move_category": "Defense",
            "energy_cost": 2,
            "power": null,
            "description": "Counter Attack: Interrupt the countered move and deal 75 power physical damage."
        },
        {
            "id": 339,
            "name": "Energy Wave",
            "move_type": {
                "id": 12,
                "name": "Fighting",
                "localized": {
                    "zh": "武"
                }
            },
            "localized": {
                "zh": {
                    "name": "气波",
                    "description": "对敌方精灵造成魔法伤害。"
                }
            },
            "move_category": "Magic Attack",
            "energy_cost": 0,
            "power": 40,
            "description": "Deals magic damage to the opponent."
        },
        {
            "id": 330,
            "name": "Momentum Stacking",
            "move_type": {
                "id": 12,
                "name": "Fighting",
                "localized": {
                    "zh": "武"
                }
            },
            "localized": {
                "zh": {
                    "name": "叠势",
                    "description": "造成魔伤，2连击，每成功应对1次，本技能连击数永久+2。"
                }
            },
            "move_category": "Magic Attack",
            "energy_cost": 3,
            "power": 25,
            "description": "Deals magic damage, 2 Combo. Each time this monster performs a successful Counter, this move's Combo count +2 permanently."
        },
        {
            "id": 332,
            "name": "Defensive Counter",
            "move_type": {
                "id": 12,
                "name": "Fighting",
                "localized": {
                    "zh": "武"
                }
            },
            "localized": {
                "zh": {
                    "name": "防御反击",
                    "description": "减伤80%，应对攻击：获得全技能威力+40。"
                }
            },
            "move_category": "Defense",
            "energy_cost": 3,
            "power": null,
            "description": "Damage taken -80%. Counter Attack: gains Move Power +40."
        }
    ],
    "legacy_moves": [
        {
            "monster_id": 24,
            "type_id": 18,
            "move_id": 457
        },
        {
            "monster_id": 24,
            "type_id": 17,
            "move_id": 442
        },
        {
            "monster_id": 24,
            "type_id": 16,
            "move_id": 411
        },
        {
            "monster_id": 24,
            "type_id": 15,
            "move_id": 402
        },
        {
            "monster_id": 24,
            "type_id": 14,
            "move_id": 376
        },
        {
            "monster_id": 24,
            "type_id": 13,
            "move_id": 353
        },
        {
            "monster_id": 24,
            "type_id": 12,
            "move_id": 333
        },
        {
            "monster_id": 24,
            "type_id": 11,
            "move_id": 323
        },
        {
            "monster_id": 24,
            "type_id": 10,
            "move_id": 291
        },
        {
            "monster_id": 24,
            "type_id": 9,
            "move_id": 271
        },
        {
            "monster_id": 24,
            "type_id": 8,
            "move_id": 257
        },
        {
            "monster_id": 24,
            "type_id": 7,
            "move_id": 238
        },
        {
            "monster_id": 24,
            "type_id": 6,
            "move_id": 212
        },
        {
            "monster_id": 24,
            "type_id": 5,
            "move_id": 177
        },
        {
            "monster_id": 24,
            "type_id": 4,
            "move_id": 159
        },
        {
            "monster_id": 24,
            "type_id": 1,
            "move_id": 62
        },
        {
            "monster_id": 24,
            "type_id": 3,
            "move_id": 122
        },
        {
            "monster_id": 24,
            "type_id": 2,
            "move_id": 99
        }
    ],
    "evolution_tree": {
        "stages": [
            {
                "depth": 0,
                "monsters": [
                    {
                        "id": 21,
                        "name": "banbanke",
                        "form": "Original",
                        "localized": {
                            "zh": {
                                "form": "本来的样子",
                                "name": "板板壳"
                            }
                        },
                        "is_leader_form": false,
                        "main_type": {
                            "id": 4,
                            "name": "Water",
                            "localized": {
                                "zh": "水"
                            }
                        },
                        "sub_type": null
                    },
                    {
                        "id": 22,
                        "name": "banbanke_tuipi",
                        "form": "Molting",
                        "localized": {
                            "zh": {
                                "form": "蜕皮时的样子",
                                "name": "板板壳"
                            }
                        },
                        "is_leader_form": false,
                        "main_type": {
                            "id": 4,
                            "name": "Water",
                            "localized": {
                                "zh": "水"
                            }
                        },
                        "sub_type": null
                    }
                ]
            },
            {
                "depth": 1,
                "monsters": [
                    {
                        "id": 23,
                        "name": "kakake",
                        "form": "Original",
                        "localized": {
                            "zh": {
                                "form": "本来的样子",
                                "name": "咔咔壳"
                            }
                        },
                        "is_leader_form": false,
                        "main_type": {
                            "id": 4,
                            "name": "Water",
                            "localized": {
                                "zh": "水"
                            }
                        },
                        "sub_type": null
                    },
                    {
                        "id": 24,
                        "name": "kakake_tuipi",
                        "form": "Molting",
                        "localized": {
                            "zh": {
                                "form": "蜕皮时的样子",
                                "name": "咔咔壳"
                            }
                        },
                        "is_leader_form": false,
                        "main_type": {
                            "id": 4,
                            "name": "Water",
                            "localized": {
                                "zh": "水"
                            }
                        },
                        "sub_type": null
                    }
                ]
            },
            {
                "depth": 2,
                "monsters": [
                    {
                        "id": 25,
                        "name": "shuipaoke",
                        "form": "Original",
                        "localized": {
                            "zh": {
                                "form": "本来的样子",
                                "name": "水泡壳"
                            }
                        },
                        "is_leader_form": false,
                        "main_type": {
                            "id": 4,
                            "name": "Water",
                            "localized": {
                                "zh": "水"
                            }
                        },
                        "sub_type": null
                    },
                    {
                        "id": 26,
                        "name": "shuipaoke_tuipi",
                        "form": "Molting",
                        "localized": {
                            "zh": {
                                "form": "蜕皮时的样子",
                                "name": "水泡壳"
                            }
                        },
                        "is_leader_form": false,
                        "main_type": {
                            "id": 4,
                            "name": "Water",
                            "localized": {
                                "zh": "水"
                            }
                        },
                        "sub_type": null
                    }
                ]
            }
        ],
        "max_depth": 2,
        "total_unique_monsters": 6,
        "species_id": 6,
        "current_monster_id": 24
    },
    "world_profile": {
        "type_desc": "硬壳精灵",
        "description_habitat": "常见于湖泊",
        "introduction": "很少再缩进壳里，即使遇到危险也会勇敢面对。甲壳内一部分是空气，一部分是水，通过喷嘴来调节重量从而在水中下潜和上浮。",
        "refresh_locations": [
            "奥贝斯坦湖",
            "轻风山"
        ],
        "movement_type": "步行",
        "classis_id": 6,
        "classis_name": "自然类精灵",
        "handbook_area_ids": [
            1,
            2
        ]
    },
    "breeding": null,
    "breeding_profile": {
        "pet_base_id": 3056,
        "egg_groups": [
            3
        ],
        "proportion_male": 5,
        "male_rate": 50,
        "female_rate": 50
    }
}
